{
  "$schema": "http://json-schema.org/draft-07/schema#",
  "description": "Create a new SQL user",
  "properties": {
    "parameters": {
      "description": "struct for passing parameters to the method [`cockroach_cloud_create_sql_user`]",
      "properties": {
        "cluster_id": {
          "type": "string"
        },
        "create_sql_user_request": {
          "$ref": "#/definitions/CreateSqlUserRequest"
        }
      },
      "required": [
        "cluster_id",
        "create_sql_user_request"
      ],
      "title": "CockroachCloudCreateSqlUserParams",
      "type": "object"
    }
  },
  "title": "cockroachdb_cockroach_cloud_create_sql_user",
  "type": "object"
}